LICENSE.txt
README.md
setup.py
jplib.egg-info/PKG-INFO
jplib.egg-info/SOURCES.txt
jplib.egg-info/dependency_links.txt
jplib.egg-info/top_level.txt
src/__init__.py
src/hash.py