Metadata-Version: 2.1
Name: jplib
Version: 0.0.1
Summary: hash functions for ccxt-lib
Author: author
License-File: LICENSE.txt
